{
    "kind": "Template",
    "apiVersion": "v1",
    "metadata": {
        "name": "report-api",
        "creationTimestamp": null
    },
    "objects": [
        {
            "kind": "Service",
            "apiVersion": "v1",
            "metadata": {
                "name": "report-api",
                "creationTimestamp": null,
                "labels": {
                    "app": "report-api"
                },
                "annotations": {
                    "openshift.io/generated-by": "OpenShiftWebConsole"
                }
            },
            "spec": {
                "ports": [
                    {
                        "name": "8080-tcp",
                        "protocol": "TCP",
                        "port": 8080,
                        "targetPort": 5010
                    }
                ],
                "selector": {
                    "deploymentconfig": "report-api"
                },
                "type": "ClusterIP",
                "sessionAffinity": "None"
            },
            "status": {
                "loadBalancer": {}
            }
        }
    ]
}
